explorer/__init__.py
explorer/admin.py
explorer/apps.py
explorer/tests.py
explorer/urls.py
explorer/migrations/0001_initial.py
explorer/migrations/0002_option.py
explorer/migrations/0003_userrole.py
explorer/migrations/0004_auto_20221117_1449.py
explorer/migrations/0005_rename_opertations_userrole_actions.py
explorer/migrations/0006_auto_20230215_1122.py
explorer/migrations/__init__.py
explorer/models/__init__.py
explorer/models/action.py
explorer/models/user_role.py
explorer/models/volume.py
explorer/static/bootstrap/css/bootstrap.min.css
explorer/static/bootstrap/js/bootstrap.bundle.min.js
explorer/static/explorer/action.css
explorer/static/explorer/action.js
explorer/static/explorer/checkbox.js
explorer/static/explorer/common.js
explorer/static/explorer/icons.css
explorer/static/explorer/navigation.css
explorer/static/explorer/onload.js
explorer/static/explorer/summary.css
explorer/static/explorer/volume.css
explorer/static/explorer/volume.js
explorer/templates/explorer/about.html
explorer/templates/explorer/base.html
explorer/templates/explorer/error.html
explorer/templates/explorer/index.html
explorer/templates/explorer/login.html
explorer/templates/explorer/logout.html
explorer/templates/explorer/warning.html
explorer/views/__init__.py
explorer/views/about.py
explorer/views/login.py
explorer/views/logout.py
explorer/views/main.py
explorer/views/extractor/__init__.py
explorer/views/extractor/location.py
explorer/views/extractor/request.py
explorer/views/extractor/user.py
explorer/views/logger/__init__.py
explorer/views/logger/logger.py
explorer/views/operations/__init__.py
explorer/views/operations/action.py
explorer/views/operations/explorer.py
explorer/views/operations/location.py
explorer/views/utils/__init__.py
explorer/views/utils/path.py
explorer/views/validator/__init__.py
explorer/views/validator/request.py
django_file_explorer-1.6.1.dist-info/METADATA
django_file_explorer-1.6.1.dist-info/WHEEL
django_file_explorer-1.6.1.dist-info/top_level.txt
django_file_explorer-1.6.1.dist-info/RECORD
