Metadata-Version: 2.1
Name: django-file-explorer
Version: 1.6.1
Summary: Django app to explore directory.
Author: Tahir Rafique
Author-email: tahirrafiqueasad@gmail.com
License: MIT
Keywords: explorer,file explorer,directory explorer,django explorer,location explorer
Classifier: Framework :: Django :: 3.2
Classifier: Topic :: Software Development :: Libraries :: Python Modules
Classifier: Development Status :: 5 - Production/Stable
Classifier: License :: OSI Approved :: MIT License
Classifier: Programming Language :: Python :: 3
Classifier: Programming Language :: Python :: 3.7
Classifier: Programming Language :: Python :: 3.8
Classifier: Operating System :: OS Independent
Classifier: Environment :: Web Environment
Classifier: Intended Audience :: Developers
Classifier: Intended Audience :: Science/Research
Classifier: Intended Audience :: Information Technology
Classifier: Natural Language :: English
Requires-Dist: requests
Requires-Dist: vscode-icons
Requires-Dist: django (>=3.2.10)
Requires-Dist: psycopg2-binary (>=2.9.5)
